{"type": "FeatureCollection", "id": "http://atlantgis.squirrel.link/ontology#Elasippos", "name": "Elasippos", "features": [{"type": "Feature", "id": "http://atlantgis.squirrel.link/data/site/G", "name": "", "dateprops": [], "properties": {"http://atlantgis.squirrel.link/ontology#archont": ["http://atlantgis.squirrel.link/ontology#Elasippos"], "http://atlantgis.squirrel.link/ontology#groupid": ["4"], "http://atlantgis.squirrel.link/ontology#gruben": ["9"], "http://atlantgis.squirrel.link/ontology#keramik1": ["2"], "http://atlantgis.squirrel.link/ontology#keramik2": ["32"], "http://atlantgis.squirrel.link/ontology#keramik3": ["23"], "http://atlantgis.squirrel.link/ontology#silex": ["1"], "http://rdfs.org/ns/void#inDataset": ["http://atlantgis.squirrel.link/data/atlantgis_dataset"], "http://www.opengis.net/ont/geosparql#hasGeometry": ["http://atlantgis.squirrel.link/data/site/G_geom"], "http://www.w3.org/1999/02/22-rdf-syntax-ns#type": ["http://atlantgis.squirrel.link/ontology#Site"], "http://www.w3.org/2000/01/rdf-schema#label": ["\u1f18\u03bb\u03ac\u03c3\u03b9\u03c0\u03c0\u03bf\u03c2"]}, "geometry": {"type": "Point", "coordinates": [-15.082751326646484, 35.499733072205636], "crs": "4326"}, "crs": "EPSG:4326"}], "numberMatched": 1, "numberReturned": 1, "bbox": [-15.082751326646484, 35.499733072205636, -15.082751326646484, 35.499733072205636], "crs": "http://www.opengis.net/def/crs/EPSG/0/EPSG:4326"}